lovebrew/__init__.py
lovebrew/__main__.py
lovebrew/console/__init__.py
lovebrew/console/console.py
lovebrew/console/ctr.py
lovebrew/console/nx.py
lovebrew/data/__init__.py
lovebrew/data/config.py
lovebrew/data/constants.py
lovebrew/data/meta/__init__.py
lovebrew/data/meta/icon.jpg
lovebrew/data/meta/icon.png
lovebrew/data/meta/lovebrew.toml
lovebrew-0.2.10.dist-info/LICENSE
lovebrew-0.2.10.dist-info/METADATA
lovebrew-0.2.10.dist-info/WHEEL
lovebrew-0.2.10.dist-info/entry_points.txt
lovebrew-0.2.10.dist-info/top_level.txt
lovebrew-0.2.10.dist-info/RECORD
