Metadata-Version: 2.1
Name: lovebrew
Version: 0.2.10
Summary: Löve Potion Game Helper
Home-page: https://github.com/TurtleP/lovebrew
Author: TurtleP
Author-email: jpostelnek@outlook.com
License: MIT
Platform: UNKNOWN
Classifier: Programming Language :: Python :: 3
Classifier: License :: OSI Approved :: MIT License
Classifier: Operating System :: POSIX :: Linux
Requires-Python: >=3.8.0
Requires-Dist: toml (>=0.10)
